{"version":2,"features":[{"name":"OilResource","id":2194,"position":[7872,4672],"rotation":0},{"name":"BarbHUT","id":2305,"position":[8640,4544],"rotation":0},{"name":"OilResource","id":2443,"position":[2752,9664],"rotation":0},{"name":"Boulder1","id":2208,"position":[11584,5184],"rotation":0},{"name":"Boulder1","id":2205,"position":[11072,8768],"rotation":0},{"name":"OilResource","id":2493,"position":[832,8640],"rotation":0},{"name":"BarbWarehouse3","id":2307,"position":[10048,4544],"rotation":0},{"name":"BarbHUT","id":2337,"position":[9536,5056],"rotation":0},{"name":"Pylon","id":2516,"position":[6080,2880],"rotation":16384},{"name":"OilResource","id":2201,"position":[8896,7488],"rotation":0},{"name":"Boulder1","id":2478,"position":[704,3520],"rotation":0},{"name":"Boulder1","id":2253,"position":[10816,4288],"rotation":0},{"name":"Boulder3","id":2227,"position":[6336,2880],"rotation":0},{"name":"Boulder2","id":2237,"position":[8384,1856],"rotation":0},{"name":"Boulder2","id":2257,"position":[10432,4672],"rotation":0},{"name":"OilResource","id":2200,"position":[9408,5568],"rotation":0},{"name":"BarbHUT","id":2385,"position":[6464,1344],"rotation":0},{"name":"Boulder3","id":2523,"position":[2752,3648],"rotation":0},{"name":"Boulder3","id":2196,"position":[6464,6208],"rotation":0},{"name":"BarbHUT","id":2388,"position":[6464,1216],"rotation":0},{"name":"OilResource","id":2483,"position":[3392,5568],"rotation":0},{"name":"Pylon","id":2492,"position":[6080,9408],"rotation":16384},{"name":"BarbHUT","id":2425,"position":[6976,10048],"rotation":0},{"name":"Boulder1","id":2491,"position":[1088,192],"rotation":0},{"name":"Boulder3","id":2463,"position":[5184,2112],"rotation":0},{"name":"Boulder2","id":2462,"position":[3264,960],"rotation":0},{"name":"Ruin3","id":2772,"position":[2496,3392],"rotation":0},{"name":"Boulder2","id":2261,"position":[10432,6336],"rotation":0},{"name":"Boulder2","id":2502,"position":[4416,1984],"rotation":0},{"name":"Pylon","id":2460,"position":[6080,4160],"rotation":16384},{"name":"OilResource","id":2506,"position":[2240,2496],"rotation":0},{"name":"Boulder2","id":2518,"position":[5440,320],"rotation":0},{"name":"BarbHUT","id":2418,"position":[6848,9280],"rotation":0},{"name":"Boulder1","id":2510,"position":[64,1216],"rotation":0},{"name":"Boulder1","id":2520,"position":[3520,6208],"rotation":0},{"name":"Ruin4","id":2495,"position":[1600,3008],"rotation":0},{"name":"Boulder2","id":2507,"position":[1088,5056],"rotation":0},{"name":"BarbHUT","id":2394,"position":[6464,1856],"rotation":0},{"name":"Boulder2","id":2480,"position":[448,2880],"rotation":0},{"name":"OilResource","id":2188,"position":[7616,2368],"rotation":0},{"name":"Boulder2","id":2206,"position":[8512,9152],"rotation":0},{"name":"Boulder3","id":2251,"position":[10304,3136],"rotation":0},{"name":"Ruin1","id":2485,"position":[1472,2880],"rotation":0},{"name":"Boulder1","id":2512,"position":[1856,9536],"rotation":0},{"name":"Boulder1","id":2473,"position":[192,5056],"rotation":0},{"name":"Pylon","id":2289,"position":[7360,3264],"rotation":0},{"name":"Pylon","id":2527,"position":[6080,6336],"rotation":16384},{"name":"BarbHUT","id":2310,"position":[9664,4928],"rotation":0},{"name":"Boulder2","id":2467,"position":[320,2240],"rotation":0},{"name":"BarbHUT","id":2326,"position":[9408,3648],"rotation":0},{"name":"Boulder2","id":2449,"position":[5312,5440],"rotation":0},{"name":"Boulder2","id":2271,"position":[7872,7744],"rotation":0},{"name":"Boulder1","id":2197,"position":[11840,6592],"rotation":0},{"name":"Boulder2","id":2508,"position":[576,704],"rotation":0},{"name":"Boulder2","id":2209,"position":[11328,7616],"rotation":0},{"name":"Boulder3","id":2515,"position":[2624,4544],"rotation":0},{"name":"BarbWarehouse2","id":2313,"position":[8704,4928],"rotation":0},{"name":"Boulder3","id":2242,"position":[10432,448],"rotation":0},{"name":"OilTower","id":2302,"position":[9536,3776],"rotation":0},{"name":"Boulder1","id":2466,"position":[4416,9536],"rotation":0},{"name":"OilTower","id":2288,"position":[8768,4544],"rotation":0},{"name":"Boulder2","id":2233,"position":[6976,3136],"rotation":0},{"name":"Pylon","id":2475,"position":[6080,7232],"rotation":16384},{"name":"BarbHUT","id":2335,"position":[9408,4928],"rotation":0},{"name":"BarbHUT","id":2395,"position":[6592,1856],"rotation":0},{"name":"BarbHUT","id":2339,"position":[9152,4928],"rotation":0},{"name":"Boulder1","id":2238,"position":[8640,1344],"rotation":0},{"name":"BarbWarehouse3","id":2488,"position":[6080,1344],"rotation":0},{"name":"BarbHUT","id":2389,"position":[6592,1216],"rotation":0},{"name":"BarbHUT","id":2421,"position":[6720,10048],"rotation":0},{"name":"WaterTower","id":2392,"position":[6592,1344],"rotation":0},{"name":"Ruin5","id":2500,"position":[1472,3008],"rotation":0},{"name":"Boulder1","id":2235,"position":[6720,3776],"rotation":0},{"name":"Boulder3","id":2236,"position":[8768,2368],"rotation":0},{"name":"Ruin4","id":2773,"position":[2624,3392],"rotation":0},{"name":"Pylon","id":2451,"position":[6080,6720],"rotation":16384},{"name":"miruin2","id":2775,"position":[2496,3648],"rotation":0},{"name":"Boulder2","id":2513,"position":[2880,6592],"rotation":0},{"name":"Pylon","id":2504,"position":[6080,5056],"rotation":16384},{"name":"Pylon","id":2300,"position":[6464,3264],"rotation":0},{"name":"OilResource","id":2472,"position":[832,1088],"rotation":0},{"name":"Boulder3","id":2198,"position":[11584,8384],"rotation":0},{"name":"Boulder1","id":2244,"position":[11712,448],"rotation":0},{"name":"BarbHUT","id":2311,"position":[8768,4672],"rotation":0},{"name":"BarbWarehouse3","id":2306,"position":[9920,4416],"rotation":0},{"name":"BarbHUT","id":2277,"position":[9536,4928],"rotation":0},{"name":"BarbWarehouse3","id":2308,"position":[9920,4544],"rotation":0},{"name":"BarbWarehouse3","id":2309,"position":[10048,4416],"rotation":0},{"name":"Boulder3","id":2234,"position":[7104,3776],"rotation":0},{"name":"Pylon","id":2299,"position":[8768,3264],"rotation":0},{"name":"BarbHUT","id":2327,"position":[8256,5056],"rotation":0},{"name":"Boulder2","id":2243,"position":[11328,1344],"rotation":0},{"name":"BarbHUT","id":2331,"position":[8384,4928],"rotation":0},{"name":"Ruin1","id":2771,"position":[2496,3520],"rotation":0},{"name":"BarbHUT","id":2330,"position":[8384,5056],"rotation":0},{"name":"Boulder1","id":2255,"position":[10176,3648],"rotation":0},{"name":"Boulder1","id":2204,"position":[7616,6592],"rotation":0},{"name":"OilResource","id":2192,"position":[9536,4544],"rotation":0},{"name":"BarbHUT","id":2287,"position":[9536,3648],"rotation":0},{"name":"BarbHUT","id":2387,"position":[6336,1216],"rotation":0},{"name":"Ruin3","id":2778,"position":[2752,3264],"rotation":0},{"name":"Boulder2","id":2486,"position":[4416,4672],"rotation":0},{"name":"Boulder1","id":2465,"position":[3264,7232],"rotation":0},{"name":"Boulder1","id":2503,"position":[192,9024],"rotation":0},{"name":"Boulder1","id":2256,"position":[9792,5184],"rotation":0},{"name":"BarbHUT","id":2304,"position":[9664,5056],"rotation":0},{"name":"BarbWarehouse1","id":2343,"position":[9088,3904],"rotation":0},{"name":"BarbHUT","id":2390,"position":[6720,1216],"rotation":0},{"name":"Boulder2","id":2479,"position":[960,10048],"rotation":0},{"name":"Boulder1","id":2203,"position":[10176,7744],"rotation":0},{"name":"BarbHUT","id":2370,"position":[9408,3776],"rotation":0},{"name":"Boulder2","id":2380,"position":[7488,1600],"rotation":0},{"name":"Boulder2","id":2521,"position":[4160,3392],"rotation":0},{"name":"Pylon","id":2290,"position":[6848,3264],"rotation":0},{"name":"BarbHUT","id":2298,"position":[8640,4672],"rotation":0},{"name":"BarbHUT","id":2422,"position":[6848,10048],"rotation":0},{"name":"Boulder1","id":2453,"position":[5312,3648],"rotation":0},{"name":"Boulder3","id":2484,"position":[2624,448],"rotation":0},{"name":"BarbWarehouse2","id":2391,"position":[6528,1088],"rotation":0},{"name":"Boulder2","id":2525,"position":[4544,8000],"rotation":0},{"name":"Ruin5","id":2776,"position":[2752,3392],"rotation":0},{"name":"WreckedTankerV","id":2452,"position":[2112,2560],"rotation":0},{"name":"Pylon","id":2501,"position":[6080,2496],"rotation":16384},{"name":"Pylon","id":2285,"position":[7872,3264],"rotation":0},{"name":"Boulder2","id":2519,"position":[3392,1216],"rotation":0},{"name":"Boulder3","id":2254,"position":[10432,4288],"rotation":0},{"name":"Pylon","id":2474,"position":[6080,3264],"rotation":24576},{"name":"Boulder2","id":2207,"position":[11840,4032],"rotation":0},{"name":"Boulder2","id":2447,"position":[5056,6848],"rotation":0},{"name":"Pylon","id":2471,"position":[6080,2112],"rotation":16384},{"name":"Boulder1","id":2246,"position":[8128,1088],"rotation":0},{"name":"BarbWarehouse3","id":2328,"position":[10048,4672],"rotation":0},{"name":"BarbHUT","id":2325,"position":[9024,4928],"rotation":0},{"name":"BarbHUT","id":2345,"position":[9024,5056],"rotation":0},{"name":"Boulder1","id":2489,"position":[2240,6208],"rotation":0},{"name":"Pylon","id":2469,"position":[6080,5824],"rotation":16384},{"name":"Boulder2","id":2457,"position":[320,6720],"rotation":0},{"name":"BarbWarehouse3","id":2384,"position":[6208,1344],"rotation":0},{"name":"Boulder1","id":2258,"position":[8768,4416],"rotation":0},{"name":"OilResource","id":2186,"position":[7104,9280],"rotation":0},{"name":"Boulder3","id":2528,"position":[3136,2624],"rotation":0},{"name":"Pylon","id":2459,"position":[6080,9152],"rotation":16384},{"name":"Pylon","id":2297,"position":[9024,3264],"rotation":0},{"name":"Boulder3","id":2458,"position":[2112,8128],"rotation":0},{"name":"WreckedVertCampVan","id":2494,"position":[1856,2880],"rotation":0},{"name":"Boulder2","id":2530,"position":[704,2112],"rotation":0},{"name":"Boulder3","id":2241,"position":[6592,832],"rotation":0},{"name":"Boulder1","id":2260,"position":[8512,4160],"rotation":0},{"name":"Boulder3","id":2226,"position":[8000,576],"rotation":0},{"name":"Ruin4","id":2777,"position":[2752,3520],"rotation":0},{"name":"Boulder2","id":2245,"position":[8896,64],"rotation":0},{"name":"Pylon","id":2524,"position":[6080,5440],"rotation":16384},{"name":"Pylon","id":2511,"position":[6080,4544],"rotation":16384},{"name":"Pylon","id":2312,"position":[8256,3264],"rotation":0},{"name":"OilResource","id":2529,"position":[960,1088],"rotation":0},{"name":"Boulder1","id":2272,"position":[8256,7488],"rotation":0},{"name":"Boulder1","id":2263,"position":[7744,5184],"rotation":0},{"name":"Boulder1","id":2264,"position":[6336,4928],"rotation":0},{"name":"BarbWarehouse1","id":2215,"position":[9088,3776],"rotation":0},{"name":"Boulder1","id":2191,"position":[10304,9280],"rotation":0},{"name":"Boulder3","id":2240,"position":[6336,960],"rotation":0},{"name":"OilResource","id":2190,"position":[11200,4800],"rotation":0},{"name":"Boulder3","id":2259,"position":[8128,5056],"rotation":0},{"name":"Boulder2","id":2252,"position":[11456,3520],"rotation":0},{"name":"Ruin5","id":2774,"position":[2624,3520],"rotation":0},{"name":"Pylon","id":2481,"position":[6080,8640],"rotation":16384},{"name":"OilResource","id":2189,"position":[9920,8768],"rotation":0},{"name":"BarbHUT","id":2423,"position":[7104,10048],"rotation":0},{"name":"Boulder3","id":2202,"position":[9280,6080],"rotation":0},{"name":"BarbHUT","id":2397,"position":[6464,1984],"rotation":0},{"name":"BarbHUT","id":2386,"position":[6336,1344],"rotation":0},{"name":"BarbWarehouse2","id":2346,"position":[8704,5056],"rotation":0},{"name":"BarbHUT","id":2276,"position":[8256,4928],"rotation":0},{"name":"Boulder3","id":2187,"position":[8768,6976],"rotation":0},{"name":"BarbHUT","id":2333,"position":[8384,4800],"rotation":0},{"name":"BarbHUT","id":2396,"position":[6592,1984],"rotation":0},{"name":"OldFactory","id":2318,"position":[9088,4608],"rotation":0},{"name":"OilResource","id":2239,"position":[6848,1856],"rotation":0},{"name":"BarbWarehouse3","id":2324,"position":[9920,4672],"rotation":0},{"name":"Boulder3","id":2496,"position":[1088,3776],"rotation":0},{"name":"BarbHUT","id":2419,"position":[6848,9152],"rotation":0},{"name":"BarbHUT","id":2417,"position":[6848,9408],"rotation":0},{"name":"Boulder3","id":2487,"position":[2496,6080],"rotation":0},{"name":"Boulder3","id":2454,"position":[4288,5568],"rotation":0},{"name":"Boulder1","id":2498,"position":[1600,8896],"rotation":0},{"name":"Boulder2","id":2526,"position":[1728,2240],"rotation":0},{"name":"Boulder1","id":2522,"position":[3136,1856],"rotation":0},{"name":"Boulder2","id":2270,"position":[6208,8000],"rotation":0},{"name":"Boulder2","id":2262,"position":[6592,4672],"rotation":0},{"name":"Boulder2","id":2461,"position":[1984,1216],"rotation":0},{"name":"OilResource","id":2517,"position":[3904,832],"rotation":0},{"name":"Pylon","id":2428,"position":[6080,3648],"rotation":8192},{"name":"miruin2","id":2429,"position":[1600,3136],"rotation":0},{"name":"Boulder2","id":2430,"position":[320,3904],"rotation":0},{"name":"Pylon","id":2431,"position":[6080,8128],"rotation":16384},{"name":"Pylon","id":2432,"position":[6080,7744],"rotation":16384},{"name":"Boulder3","id":2433,"position":[320,960],"rotation":0},{"name":"Boulder3","id":2436,"position":[5312,6592],"rotation":0},{"name":"Boulder1","id":2437,"position":[832,6464],"rotation":0},{"name":"Boulder2","id":2438,"position":[1216,8768],"rotation":0},{"name":"Boulder1","id":2440,"position":[4800,3648],"rotation":0},{"name":"Boulder1","id":2441,"position":[4544,576],"rotation":0},{"name":"Boulder3","id":2442,"position":[4032,3008],"rotation":0},{"name":"Boulder2","id":2470,"position":[2624,9408],"rotation":0},{"name":"Boulder1","id":2444,"position":[3904,320],"rotation":0},{"name":"Ruin3","id":2446,"position":[1600,2880],"rotation":0},{"name":"AirTrafficControl","id":3120,"position":[6336,8256],"rotation":0},{"name":"AirTrafficControl","id":3121,"position":[8000,9280],"rotation":0},{"name":"AirTrafficControl","id":3119,"position":[5056,9408],"rotation":0},{"name":"Ruin1","id":3482,"position":[10816,7616],"rotation":0},{"name":"Ruin3","id":3470,"position":[10432,8000],"rotation":0},{"name":"Ruin1","id":3468,"position":[10304,7744],"rotation":0},{"name":"Boulder3","id":3125,"position":[8640,11584],"rotation":32768},{"name":"Boulder3","id":3414,"position":[9664,14272],"rotation":32768},{"name":"OilResource","id":3128,"position":[11328,11712],"rotation":32768},{"name":"BarbWarehouse3","id":3484,"position":[10432,7360],"rotation":0},{"name":"Boulder1","id":3326,"position":[9920,14144],"rotation":32768},{"name":"OilResource","id":3440,"position":[9408,10688],"rotation":32768},{"name":"miruin2","id":3466,"position":[10432,7872],"rotation":0},{"name":"Boulder1","id":3136,"position":[11456,16832],"rotation":32768},{"name":"Boulder1","id":3282,"position":[11968,11328],"rotation":32768},{"name":"Ruin3","id":3481,"position":[10816,7744],"rotation":0},{"name":"Ruin5","id":3307,"position":[9408,16960],"rotation":32768},{"name":"BarbHUT","id":3445,"position":[6720,10176],"rotation":0},{"name":"Ruin5","id":3473,"position":[10304,7872],"rotation":0},{"name":"Boulder3","id":3144,"position":[9408,16704],"rotation":32768},{"name":"Boulder3","id":3411,"position":[11072,16576],"rotation":32768},{"name":"Boulder3","id":3439,"position":[8128,17344],"rotation":32768},{"name":"Boulder2","id":3417,"position":[10432,18112],"rotation":32768},{"name":"WreckedTankerV","id":3308,"position":[10048,17792],"rotation":32768},{"name":"OilResource","id":3149,"position":[8768,14784],"rotation":32768},{"name":"miruin2","id":3465,"position":[10432,8128],"rotation":0},{"name":"Boulder1","id":3438,"position":[7616,19776],"rotation":32768},{"name":"Boulder1","id":3153,"position":[11072,20160],"rotation":32768},{"name":"WaterTower","id":3493,"position":[10944,7360],"rotation":0},{"name":"Boulder1","id":3418,"position":[9024,18496],"rotation":32768},{"name":"Boulder3","id":3157,"position":[6976,18240],"rotation":32768},{"name":"Boulder2","id":3158,"position":[8896,19392],"rotation":32768},{"name":"Ruin3","id":3159,"position":[9664,16960],"rotation":32768},{"name":"Ruin1","id":3467,"position":[10432,7616],"rotation":0},{"name":"Boulder2","id":3319,"position":[7104,13504],"rotation":32768},{"name":"Boulder2","id":3421,"position":[10176,19136],"rotation":32768},{"name":"Boulder2","id":3163,"position":[7744,18368],"rotation":32768},{"name":"Ruin4","id":3480,"position":[10816,7872],"rotation":0},{"name":"miruin2","id":3476,"position":[10048,8128],"rotation":0},{"name":"OilResource","id":3166,"position":[9920,17856],"rotation":32768},{"name":"Boulder2","id":3167,"position":[6720,20032],"rotation":32768},{"name":"Boulder1","id":3437,"position":[7360,16704],"rotation":32768},{"name":"WreckedVertCampVan","id":3347,"position":[10304,17472],"rotation":32768},{"name":"AirTrafficControl","id":3462,"position":[7104,10944],"rotation":32768},{"name":"Boulder1","id":3173,"position":[12096,19136],"rotation":32768},{"name":"Boulder1","id":3174,"position":[8640,14144],"rotation":32768},{"name":"Ruin4","id":3175,"position":[10560,17344],"rotation":32768},{"name":"Boulder2","id":3176,"position":[11072,15296],"rotation":32768},{"name":"Ruin5","id":3474,"position":[10304,8128],"rotation":0},{"name":"Boulder2","id":3179,"position":[11712,17472],"rotation":32768},{"name":"WaterTower","id":3494,"position":[10176,7616],"rotation":0},{"name":"BarbWarehouse3","id":3483,"position":[10816,7360],"rotation":0},{"name":"Ruin5","id":3479,"position":[9920,8128],"rotation":0},{"name":"OilResource","id":3361,"position":[11200,19264],"rotation":32768},{"name":"BarbWarehouse3","id":3485,"position":[10432,8384],"rotation":0},{"name":"Boulder3","id":3303,"position":[9536,19904],"rotation":32768},{"name":"Ruin1","id":3188,"position":[10688,17472],"rotation":32768},{"name":"Boulder1","id":3189,"position":[10304,10816],"rotation":32768},{"name":"Boulder1","id":3190,"position":[11968,15296],"rotation":32768},{"name":"Boulder2","id":3313,"position":[8768,19136],"rotation":32768},{"name":"Ruin3","id":3478,"position":[10176,8128],"rotation":0},{"name":"Ruin5","id":3377,"position":[9536,16832],"rotation":32768},{"name":"Boulder1","id":3416,"position":[10560,11456],"rotation":32768},{"name":"Boulder2","id":3196,"position":[11840,18112],"rotation":32768},{"name":"Ruin4","id":3472,"position":[10304,8000],"rotation":0},{"name":"Boulder2","id":3198,"position":[6848,14912],"rotation":32768},{"name":"BarbWarehouse3","id":3486,"position":[10816,8128],"rotation":0},{"name":"miruin2","id":3426,"position":[10560,17216],"rotation":32768},{"name":"OilResource","id":3422,"position":[8256,19520],"rotation":32768},{"name":"Boulder3","id":3433,"position":[6848,13760],"rotation":32768},{"name":"Boulder2","id":3306,"position":[7616,12352],"rotation":32768},{"name":"Boulder2","id":3204,"position":[11584,19648],"rotation":32768},{"name":"Boulder3","id":3430,"position":[11840,19392],"rotation":32768},{"name":"Boulder3","id":3206,"position":[9536,15808],"rotation":32768},{"name":"Ruin3","id":3469,"position":[10304,7616],"rotation":0},{"name":"Boulder2","id":3289,"position":[11200,10304],"rotation":32768},{"name":"Boulder3","id":3343,"position":[9024,17728],"rotation":32768},{"name":"Boulder1","id":3434,"position":[11328,13888],"rotation":32768},{"name":"Boulder1","id":3211,"position":[7744,10816],"rotation":32768},{"name":"Boulder1","id":3441,"position":[8256,20032],"rotation":32768},{"name":"BarbWarehouse3","id":3487,"position":[10304,7360],"rotation":0},{"name":"Boulder2","id":3296,"position":[8000,16960],"rotation":32768},{"name":"Boulder3","id":3346,"position":[10048,12224],"rotation":32768},{"name":"Ruin5","id":3490,"position":[10304,6976],"rotation":0},{"name":"Boulder2","id":3435,"position":[10944,11584],"rotation":32768},{"name":"Ruin1","id":3477,"position":[10048,8000],"rotation":0},{"name":"Boulder2","id":3305,"position":[9536,10944],"rotation":32768},{"name":"Boulder2","id":3280,"position":[7744,15680],"rotation":32768},{"name":"Boulder2","id":3348,"position":[11456,18240],"rotation":32768},{"name":"Ruin4","id":3354,"position":[9408,16832],"rotation":32768},{"name":"Boulder1","id":3281,"position":[8896,13120],"rotation":32768},{"name":"Ruin3","id":3488,"position":[10432,7104],"rotation":0},{"name":"Ruin1","id":3270,"position":[9664,16832],"rotation":32768},{"name":"Boulder2","id":3427,"position":[11840,16448],"rotation":32768},{"name":"Ruin4","id":3471,"position":[10432,7744],"rotation":0},{"name":"Ruin5","id":3236,"position":[10688,17344],"rotation":32768},{"name":"Boulder1","id":3300,"position":[6848,16704],"rotation":32768},{"name":"Ruin3","id":3279,"position":[9408,17088],"rotation":32768},{"name":"Ruin4","id":3239,"position":[9536,16960],"rotation":32768},{"name":"Boulder3","id":3415,"position":[7872,14784],"rotation":32768},{"name":"Boulder2","id":3331,"position":[11840,13632],"rotation":32768},{"name":"miruin2","id":3243,"position":[9664,16704],"rotation":32768},{"name":"Boulder2","id":3244,"position":[9280,13760],"rotation":32768},{"name":"miruin2","id":3491,"position":[10304,7104],"rotation":0},{"name":"miruin2","id":3475,"position":[10176,8000],"rotation":0},{"name":"Ruin4","id":3489,"position":[10432,6976],"rotation":0},{"name":"OilResource","id":3248,"position":[11328,19264],"rotation":32768},{"name":"Ruin3","id":3443,"position":[10560,17472],"rotation":32768},{"name":"WaterTower","id":3492,"position":[10048,8384],"rotation":0},{"name":"OilResource","id":3496,"position":[4288,15680],"rotation":32768},{"name":"BarbHUT","id":3497,"position":[3520,15808],"rotation":32768},{"name":"Boulder1","id":3498,"position":[576,15168],"rotation":32768},{"name":"Boulder1","id":3499,"position":[1088,11584],"rotation":32768},{"name":"BarbWarehouse3","id":3501,"position":[2112,15808],"rotation":32768},{"name":"BarbHUT","id":3502,"position":[2624,15296],"rotation":32768},{"name":"Pylon","id":3503,"position":[6080,17472],"rotation":49152},{"name":"OilResource","id":3505,"position":[3264,12864],"rotation":32768},{"name":"Boulder1","id":3507,"position":[1344,16064],"rotation":32768},{"name":"Boulder3","id":3508,"position":[5824,17472],"rotation":32768},{"name":"Boulder2","id":3509,"position":[3776,18496],"rotation":32768},{"name":"Boulder2","id":3511,"position":[1728,15680],"rotation":32768},{"name":"OilResource","id":3512,"position":[2752,14784],"rotation":32768},{"name":"BarbHUT","id":3513,"position":[5696,19008],"rotation":32768},{"name":"Boulder3","id":3516,"position":[5696,14144],"rotation":32768},{"name":"BarbHUT","id":3517,"position":[5696,19136],"rotation":32768},{"name":"Pylon","id":3518,"position":[6080,10944],"rotation":49152},{"name":"BarbHUT","id":3519,"position":[5184,10304],"rotation":32768},{"name":"Boulder2","id":3526,"position":[1728,14016],"rotation":32768},{"name":"Pylon","id":3527,"position":[6080,16192],"rotation":49152},{"name":"BarbHUT","id":3531,"position":[5312,11072],"rotation":32768},{"name":"BarbHUT","id":3532,"position":[5696,18496],"rotation":32768},{"name":"OilResource","id":3534,"position":[4544,17984],"rotation":32768},{"name":"Boulder2","id":3536,"position":[3648,11200],"rotation":32768},{"name":"Boulder3","id":3538,"position":[1856,17216],"rotation":32768},{"name":"Pylon","id":3542,"position":[4800,17088],"rotation":32768},{"name":"Pylon","id":3545,"position":[6080,14016],"rotation":49152},{"name":"BarbHUT","id":3546,"position":[2496,15424],"rotation":32768},{"name":"BarbHUT","id":3547,"position":[2752,16704],"rotation":32768},{"name":"Boulder2","id":3549,"position":[4288,12608],"rotation":32768},{"name":"Boulder1","id":3550,"position":[320,13760],"rotation":32768},{"name":"Boulder2","id":3553,"position":[832,12736],"rotation":32768},{"name":"BarbWarehouse2","id":3554,"position":[3456,15424],"rotation":32768},{"name":"Boulder3","id":3556,"position":[1728,19904],"rotation":32768},{"name":"OilTower","id":3557,"position":[2624,16576],"rotation":32768},{"name":"OilTower","id":3558,"position":[3392,15808],"rotation":32768},{"name":"Boulder2","id":3559,"position":[5184,17216],"rotation":32768},{"name":"Pylon","id":3561,"position":[6080,13120],"rotation":49152},{"name":"BarbHUT","id":3563,"position":[2752,15424],"rotation":32768},{"name":"BarbHUT","id":3565,"position":[5568,18496],"rotation":32768},{"name":"BarbHUT","id":3568,"position":[3008,15424],"rotation":32768},{"name":"Boulder1","id":3572,"position":[3520,19008],"rotation":32768},{"name":"BarbWarehouse3","id":3573,"position":[6080,19008],"rotation":32768},{"name":"BarbHUT","id":3574,"position":[5568,19136],"rotation":32768},{"name":"BarbHUT","id":3575,"position":[5440,10304],"rotation":32768},{"name":"WaterTower","id":3576,"position":[5568,19008],"rotation":32768},{"name":"Boulder1","id":3579,"position":[5440,16576],"rotation":32768},{"name":"Boulder3","id":3580,"position":[3392,17984],"rotation":32768},{"name":"Pylon","id":3581,"position":[6080,13632],"rotation":49152},{"name":"Pylon","id":3585,"position":[6080,15296],"rotation":49152},{"name":"Pylon","id":3586,"position":[5696,17088],"rotation":32768},{"name":"Boulder3","id":3588,"position":[576,11968],"rotation":32768},{"name":"Boulder1","id":3591,"position":[448,19904],"rotation":32768},{"name":"BarbHUT","id":3592,"position":[3392,15680],"rotation":32768},{"name":"BarbWarehouse3","id":3594,"position":[2240,15936],"rotation":32768},{"name":"BarbHUT","id":3596,"position":[2624,15424],"rotation":32768},{"name":"BarbWarehouse3","id":3600,"position":[2240,15808],"rotation":32768},{"name":"BarbWarehouse3","id":3602,"position":[2112,15936],"rotation":32768},{"name":"Boulder3","id":3603,"position":[5056,16576],"rotation":32768},{"name":"Pylon","id":3604,"position":[3392,17088],"rotation":32768},{"name":"BarbHUT","id":3605,"position":[3904,15296],"rotation":32768},{"name":"Boulder2","id":3606,"position":[832,19008],"rotation":32768},{"name":"BarbHUT","id":3607,"position":[3776,15424],"rotation":32768},{"name":"BarbHUT","id":3608,"position":[3776,15296],"rotation":32768},{"name":"Boulder1","id":3609,"position":[1984,16704],"rotation":32768},{"name":"Boulder1","id":3611,"position":[4544,13760],"rotation":32768},{"name":"OilResource","id":3612,"position":[2624,15808],"rotation":32768},{"name":"BarbHUT","id":3613,"position":[2624,16704],"rotation":32768},{"name":"BarbHUT","id":3614,"position":[5824,19136],"rotation":32768},{"name":"Boulder1","id":3616,"position":[2368,15168],"rotation":32768},{"name":"BarbHUT","id":3618,"position":[2496,15296],"rotation":32768},{"name":"BarbWarehouse1","id":3619,"position":[3072,16448],"rotation":32768},{"name":"BarbHUT","id":3620,"position":[5440,19136],"rotation":32768},{"name":"Boulder1","id":3621,"position":[1984,12608],"rotation":32768},{"name":"BarbHUT","id":3623,"position":[2752,16576],"rotation":32768},{"name":"Boulder2","id":3625,"position":[4672,18752],"rotation":32768},{"name":"Pylon","id":3626,"position":[5312,17088],"rotation":32768},{"name":"BarbHUT","id":3627,"position":[3520,15680],"rotation":32768},{"name":"BarbHUT","id":3628,"position":[5312,10304],"rotation":32768},{"name":"BarbWarehouse2","id":3630,"position":[5632,19264],"rotation":32768},{"name":"Pylon","id":3631,"position":[6080,17856],"rotation":49152},{"name":"Pylon","id":3632,"position":[4288,17088],"rotation":32768},{"name":"Boulder3","id":3634,"position":[1728,16064],"rotation":32768},{"name":"Pylon","id":3635,"position":[6080,17088],"rotation":57344},{"name":"Boulder2","id":3638,"position":[320,16320],"rotation":32768},{"name":"Pylon","id":3639,"position":[6080,18240],"rotation":49152},{"name":"Boulder1","id":3640,"position":[4032,19264],"rotation":32768},{"name":"BarbWarehouse3","id":3641,"position":[2112,15680],"rotation":32768},{"name":"BarbHUT","id":3642,"position":[3136,15424],"rotation":32768},{"name":"BarbHUT","id":3643,"position":[3136,15296],"rotation":32768},{"name":"Pylon","id":3645,"position":[6080,14528],"rotation":49152},{"name":"BarbWarehouse3","id":3654,"position":[5952,19008],"rotation":32768},{"name":"Boulder1","id":3655,"position":[3392,15936],"rotation":32768},{"name":"OilResource","id":3658,"position":[5056,11072],"rotation":32768},{"name":"Pylon","id":3659,"position":[6080,11200],"rotation":49152},{"name":"Pylon","id":3660,"position":[3136,17088],"rotation":32768},{"name":"Boulder3","id":3661,"position":[5568,19520],"rotation":32768},{"name":"Boulder1","id":3662,"position":[3648,16192],"rotation":32768},{"name":"Boulder3","id":3663,"position":[4160,19776],"rotation":32768},{"name":"Boulder2","id":3666,"position":[3264,20288],"rotation":32768},{"name":"Pylon","id":3667,"position":[6080,14912],"rotation":49152},{"name":"Pylon","id":3668,"position":[6080,15808],"rotation":49152},{"name":"Pylon","id":3669,"position":[3904,17088],"rotation":32768},{"name":"Boulder1","id":3674,"position":[3904,12864],"rotation":32768},{"name":"Boulder1","id":3675,"position":[4416,15168],"rotation":32768},{"name":"Boulder1","id":3676,"position":[5824,15424],"rotation":32768},{"name":"BarbWarehouse1","id":3678,"position":[3072,16576],"rotation":32768},{"name":"Boulder1","id":3679,"position":[1856,11072],"rotation":32768},{"name":"Boulder3","id":3680,"position":[5824,19392],"rotation":32768},{"name":"OilResource","id":3681,"position":[960,15552],"rotation":32768},{"name":"Boulder3","id":3682,"position":[4032,15296],"rotation":32768},{"name":"Boulder2","id":3685,"position":[704,16832],"rotation":32768},{"name":"Pylon","id":3688,"position":[6080,11712],"rotation":49152},{"name":"OilResource","id":3689,"position":[2240,11584],"rotation":32768},{"name":"BarbHUT","id":3692,"position":[5056,10304],"rotation":32768},{"name":"Boulder3","id":3693,"position":[2880,14272],"rotation":32768},{"name":"BarbHUT","id":3695,"position":[5696,18368],"rotation":32768},{"name":"BarbHUT","id":3697,"position":[5824,19008],"rotation":32768},{"name":"BarbWarehouse2","id":3698,"position":[3456,15296],"rotation":32768},{"name":"BarbHUT","id":3702,"position":[3904,15424],"rotation":32768},{"name":"Boulder3","id":3703,"position":[3392,13376],"rotation":32768},{"name":"BarbHUT","id":3706,"position":[3776,15552],"rotation":32768},{"name":"BarbHUT","id":3707,"position":[5568,18368],"rotation":32768},{"name":"OldFactory","id":3709,"position":[3072,15744],"rotation":32768},{"name":"OilResource","id":3711,"position":[5312,18496],"rotation":32768},{"name":"BarbWarehouse3","id":3715,"position":[2240,15680],"rotation":32768},{"name":"BarbHUT","id":3717,"position":[5312,11200],"rotation":32768},{"name":"BarbHUT","id":3718,"position":[5312,10944],"rotation":32768},{"name":"Boulder2","id":3719,"position":[5952,12352],"rotation":32768},{"name":"Boulder2","id":3720,"position":[5568,15680],"rotation":32768},{"name":"Pylon","id":3721,"position":[6080,16704],"rotation":40960},{"name":"Pylon","id":3722,"position":[6080,12224],"rotation":49152},{"name":"Pylon","id":3723,"position":[6080,12608],"rotation":49152},{"name":"AirTrafficControl","id":3724,"position":[5824,12096],"rotation":32768},{"name":"AirTrafficControl","id":3725,"position":[4160,11072],"rotation":32768},{"name":"BarbHUT","id":3727,"position":[5440,10176],"rotation":32768},{"name":"OilResource","id":3734,"position":[6080,10176],"rotation":0},{"name":"miruin2","id":3736,"position":[1728,12224],"rotation":32768},{"name":"miruin2","id":3737,"position":[1728,12480],"rotation":32768},{"name":"Ruin1","id":3738,"position":[1728,12736],"rotation":32768},{"name":"Ruin1","id":3739,"position":[1856,12608],"rotation":32768},{"name":"Ruin3","id":3740,"position":[1856,12736],"rotation":32768},{"name":"Ruin3","id":3741,"position":[1728,12352],"rotation":32768},{"name":"Ruin4","id":3742,"position":[1728,12608],"rotation":32768},{"name":"Ruin4","id":3743,"position":[1856,12352],"rotation":32768},{"name":"Ruin5","id":3744,"position":[1856,12480],"rotation":32768},{"name":"Ruin5","id":3745,"position":[1856,12224],"rotation":32768},{"name":"miruin2","id":3746,"position":[1984,12352],"rotation":32768},{"name":"miruin2","id":3747,"position":[2112,12224],"rotation":32768},{"name":"Ruin1","id":3748,"position":[2112,12352],"rotation":32768},{"name":"Ruin3","id":3749,"position":[1984,12224],"rotation":32768},{"name":"Ruin5","id":3750,"position":[2240,12224],"rotation":32768},{"name":"Ruin4","id":3751,"position":[1344,12480],"rotation":32768},{"name":"Ruin3","id":3752,"position":[1344,12608],"rotation":32768},{"name":"Ruin1","id":3753,"position":[1344,12736],"rotation":32768},{"name":"BarbWarehouse3","id":3754,"position":[1344,12992],"rotation":32768},{"name":"BarbWarehouse3","id":3755,"position":[1728,12992],"rotation":32768},{"name":"BarbWarehouse3","id":3756,"position":[1728,11968],"rotation":32768},{"name":"BarbWarehouse3","id":3757,"position":[1344,12224],"rotation":32768},{"name":"BarbWarehouse3","id":3758,"position":[1856,12992],"rotation":32768},{"name":"Ruin3","id":3759,"position":[1728,13248],"rotation":32768},{"name":"Ruin4","id":3760,"position":[1728,13376],"rotation":32768},{"name":"Ruin5","id":3761,"position":[1856,13376],"rotation":32768},{"name":"miruin2","id":3762,"position":[1856,13248],"rotation":32768},{"name":"WaterTower","id":3763,"position":[2112,11968],"rotation":32768},{"name":"WaterTower","id":3764,"position":[1216,12992],"rotation":32768},{"name":"WaterTower","id":3765,"position":[1984,12736],"rotation":32768},{"name":"Boulder3","id":2497,"position":[3520,8768],"rotation":0}]}